codemp-0.8.4.dist-info/METADATA
codemp-0.8.4.dist-info/WHEEL
codemp/codemp.pyi
codemp/__init__.py
codemp/codemp.abi3.so
codemp-0.8.4.dist-info/RECORD
