Metadata-Version: 2.3
Name: codemp
Version: 0.8.4
Classifier: Programming Language :: Python
Summary: code multiplexer
Keywords: codemp,cooperative,rust,python
Home-Page: https://code.mp
Author: alemi <me@alemi.dev>, zaaarf <me@zaaarf.foo>, frelodev <frelodev@gmail.com>, cschen <cschen@codemp.dev>
Author-email: cschen <cschen@codemp.dev>, alemi <me@alemi.dev>, zaaarf <me@zaaarf.foo>, frelodev <frelodev@gmail.com>
Maintainer-email: cschen <cschen@codemp.dev>
License: GPL-3.0-only
Requires-Python: >=3.8
Project-URL: repository, https://github.com/hexedtech/codemp.git
